setup.cfg
setup.py
jabba_analysis/__init__.py
jabba_analysis/dummy.py
jabba_analysis.egg-info/PKG-INFO
jabba_analysis.egg-info/SOURCES.txt
jabba_analysis.egg-info/dependency_links.txt
jabba_analysis.egg-info/requires.txt
jabba_analysis.egg-info/top_level.txt