Metadata-Version: 1.1
Name: jabba-analysis
Version: 0.0.1
Summary: Additional JABBA analysis functions
Home-page: https://github.com/missingdays/jabba_analysis
Author: missingdays
Author-email: rebovykin@gmail.com
License: UNKNOWN
Download-URL: https://github.com/missingdays/jabba_analysis/arhive/0.0.1.tar.gz
Keywords: JABBA,Jenkins
Platform: UNKNOWN
